nltnump/nltnump.py
nltnump-0.0.dist-info/METADATA
nltnump-0.0.dist-info/WHEEL
nltnump-0.0.dist-info/top_level.txt
nltnump-0.0.dist-info/RECORD
