Metadata-Version: 2.1
Name: nltnump
Version: 0.0
Summary: nltnump
Author-email: applepro285@gmail.com
